matrix_schema/__init__.py
matrix_schema/_version.py
matrix_schema/datamodel/__init__.py
matrix_schema/datamodel/matrix_schema.py
matrix_schema/datamodel/matrix_schema_pydantic.py
matrix_schema/datamodel/pandera-schema.py
matrix_schema/datamodel/pandera.py
matrix_schema/schema/biolink_imports.yaml
matrix_schema/schema/disease_list.yaml
matrix_schema/schema/matrix_kg.yaml
matrix_schema/schema/matrix_schema.yaml
matrix_schema/schema/valid_biolink_edge_types.tsv
matrix_schema/utils/__init__.py
matrix_schema/utils/generate_biolink_imports.py
matrix_schema/utils/generate_valid_edge_type_table.py
matrix_schema/utils/pandera_utils.py
matrix_schema-0.4.3.dist-info/LICENSE
matrix_schema-0.4.3.dist-info/METADATA
matrix_schema-0.4.3.dist-info/WHEEL
matrix_schema-0.4.3.dist-info/RECORD
