Metadata-Version: 2.3
Name: matrix_schema
Version: 0.4.3
Summary: The collected MATRIX schemas
License: BSD-3
Author: Nicolas Matentzoglu
Author-email: nicolas.matentzoglu@gmail.com
Requires-Python: >=3.9
Classifier: License :: Other/Proprietary License
Classifier: Programming Language :: Python :: 3
Classifier: Programming Language :: Python :: 3.9
Classifier: Programming Language :: Python :: 3.10
Classifier: Programming Language :: Python :: 3.11
Classifier: Programming Language :: Python :: 3.12
Classifier: Programming Language :: Python :: 3.13
Provides-Extra: docs
Requires-Dist: biolink-model (>=4.2.5,<5.0.0)
Requires-Dist: jinjanator (>=24.4.0) ; extra == "docs"
Requires-Dist: linkml-runtime (>=1.8.0)
